ai_guard/__init__.py
ai_guard/__main__.py
ai_guard/analyzer.py
ai_guard/analyzer_optimized.py
ai_guard/config.py
ai_guard/diff_parser.py
ai_guard/performance.py
ai_guard/pr_annotations.py
ai_guard/report.py
ai_guard/report_html.py
ai_guard/report_json.py
ai_guard/sarif_report.py
ai_guard/security_scanner.py
ai_guard/tests_runner.py
ai_guard/gates/__init__.py
ai_guard/gates/coverage_eval.py
ai_guard/generators/__init__.py
ai_guard/generators/config_loader.py
ai_guard/generators/enhanced_testgen.py
ai_guard/generators/testgen.py
ai_guard/language_support/js_ts_support.py
ai_guard/parsers/__init__.py
ai_guard/parsers/common.py
ai_guard/parsers/typescript.py
ai_guard/utils/__init__.py
ai_guard/utils/error_formatter.py
ai_guard/utils/subprocess_runner.py
smart_ai_guard-0.1.0.dist-info/licenses/LICENSE
smart_ai_guard-0.1.0.dist-info/METADATA
smart_ai_guard-0.1.0.dist-info/WHEEL
smart_ai_guard-0.1.0.dist-info/entry_points.txt
smart_ai_guard-0.1.0.dist-info/top_level.txt
smart_ai_guard-0.1.0.dist-info/RECORD
