Metadata-Version: 2.4
Name: smart-ai-guard
Version: 0.1.0
Summary: Smart Code Quality Gatekeeper for AI-generated code
Home-page: https://github.com/Manavj99/ai-guard
Author: AI-Guard Contributors
Author-email: contributors@ai-guard.dev
License-Expression: MIT
Keywords: code-quality,ci-cd,testing,security,ai
Classifier: Development Status :: 3 - Alpha
Classifier: Intended Audience :: Developers
Classifier: Programming Language :: Python :: 3
Classifier: Programming Language :: Python :: 3.11
Classifier: Programming Language :: Python :: 3.12
Classifier: Topic :: Software Development :: Quality Assurance
Classifier: Topic :: Software Development :: Testing
Requires-Python: >=3.11
License-File: LICENSE
Requires-Dist: typer==0.9.0
Requires-Dist: rich==13.3.5
Requires-Dist: tomli>=2.0.1
Requires-Dist: defusedxml>=0.7.1
Requires-Dist: click==8.1.7
Provides-Extra: dev
Requires-Dist: flake8>=7.1.1; extra == "dev"
Requires-Dist: mypy>=1.11.1; extra == "dev"
Requires-Dist: pytest>=8.3.2; extra == "dev"
Requires-Dist: pytest-cov>=5.0.0; extra == "dev"
Requires-Dist: bandit>=1.7.9; extra == "dev"
Requires-Dist: hypothesis>=6.112.0; extra == "dev"
Requires-Dist: pre-commit>=3.0.0; extra == "dev"
Requires-Dist: pygithub>=2.4.0; extra == "dev"
Dynamic: author-email
Dynamic: home-page
Dynamic: license-file
Dynamic: requires-python
